PySpeakItOut/__init__.py
PySpeakItOut/reader.py
PySpeakItOut-0.2.2.dist-info/METADATA
PySpeakItOut-0.2.2.dist-info/WHEEL
PySpeakItOut-0.2.2.dist-info/top_level.txt
PySpeakItOut-0.2.2.dist-info/RECORD
