Metadata-Version: 2.1
Name: PySpeakItOut
Version: 0.2.2
Summary: PySpeakItOut AudioBook package 
Home-page: UNKNOWN
Author: krishna sonune
Author-email: krishnasonune87@gmail.com
License: UNKNOWN
Keywords: python
Platform: UNKNOWN
Classifier: Development Status :: 3 - Alpha
Classifier: Intended Audience :: Education
Classifier: Programming Language :: Python :: 2
Classifier: Programming Language :: Python :: 3
Classifier: Operating System :: MacOS :: MacOS X
Classifier: Operating System :: Microsoft :: Windows
Requires-Dist: pyttsx3
Requires-Dist: PyPDF2
